{
  "values": [
    {
      "id": "create:goggles",
      "required": false
    },
    {
      "id": "environmental:thief_hood",
      "required": false
    },
    {
      "id": "quark:forgotten_hat",
      "required": false
    },
    {
      "id": "savageandravage:griefer_helmet",
      "required": false
    },
    {
      "id": "theoneprobe:iron_helmet_probe",
      "required": false
    },
    {
      "id": "theoneprobe:gold_helmet_probe",
      "required": false
    },
    {
      "id": "theoneprobe:diamond_helmet_probe",
      "required": false
    }
  ]
}
